cec/__init__.py
cec/cec.py
dvb/__init__.py
dvb/frontend.py
mediactl/__init__.py
mediactl/media.py
rc/__init__.py
rc/lirc.py
util/__init__.py
util/ctypes_tools.py
util/ioctl.py
v4l2/__init__.py
v4l2/common.py
v4l2/mediabus.py
v4l2/subdev.py
v4l2/videodev.py
uapy-1.0.2.dist-info/LICENSE
uapy-1.0.2.dist-info/METADATA
uapy-1.0.2.dist-info/WHEEL
uapy-1.0.2.dist-info/top_level.txt
uapy-1.0.2.dist-info/RECORD
