Metadata-Version: 2.1
Name: uapy
Version: 1.0.2
Summary: Python wrapper for Linux UAPI ioctl
Home-page: https://github.com/indigohedgehog/uapy
Author: Andres Castillo
Author-email: indigohedgehog@gmail.com
License: UNKNOWN
Project-URL: Bug Tracker, https://github.com/indigohedgehog/uapy/issues
Platform: UNKNOWN
Classifier: Programming Language :: Python :: 3
Classifier: License :: OSI Approved :: MIT License
Classifier: License :: OSI Approved :: GNU Lesser General Public License v3 (LGPLv3)
Classifier: License :: OSI Approved :: GNU General Public License v3 (GPLv3)
Classifier: License :: OSI Approved :: BSD License
Classifier: Operating System :: POSIX :: Linux
Classifier: Topic :: Multimedia
Classifier: Topic :: Multimedia :: Video
Requires-Python: >=3.6
